fixthis/__init__.py
fixthis/core.py
fixthis-0.1.6.dist-info/licenses/LICENSE
fixthis_internal/__init__.py
fixthis_internal/interpreter.py
fixthis_internal/name_utils.py
fixthis-0.1.6.dist-info/METADATA
fixthis-0.1.6.dist-info/WHEEL
fixthis-0.1.6.dist-info/top_level.txt
fixthis-0.1.6.dist-info/RECORD
