Metadata-Version: 2.4
Name: fixthis
Version: 0.1.6
Summary: A small Python library that provides some 'QOL' features
Author-email: Konstantin <assembly@codemania.net>
License:                     GNU GENERAL PUBLIC LICENSE
Requires-Python: <3.14,>=3.13
License-File: LICENSE
Dynamic: license-file
